exiftoolgui/__init__.py
exiftoolgui/exiftoolgui.py
exiftoolgui-0.1.5.dist-info/METADATA
exiftoolgui-0.1.5.dist-info/WHEEL
exiftoolgui-0.1.5.dist-info/entry_points.txt
exiftoolgui-0.1.5.dist-info/licenses/LICENSE
exiftoolgui-0.1.5.dist-info/RECORD
