Metadata-Version: 2.3
Name: exiftoolgui
Version: 0.1.5
Summary: A GUI application for ExifTool built with Claude 3.5 Sonnet, designed to work on Linux and macOS.
Project-URL: Homepage, https://github.com/psyb0t/exiftoolgui
Project-URL: Issues, https://github.com/psyb0t/exiftoolgui/issues
Author: Claude 3.5 Sonnet
Author-email: Ciprian Mandache <psyb0t@51k.eu>
License-File: LICENSE
Classifier: Operating System :: MacOS
Classifier: Operating System :: POSIX :: Linux
Classifier: Programming Language :: Python :: 3
Classifier: Programming Language :: Python :: 3.7
Classifier: Programming Language :: Python :: 3.8
Classifier: Programming Language :: Python :: 3.9
Classifier: Programming Language :: Python :: 3.10
Classifier: Programming Language :: Python :: 3.11
Requires-Python: >=3.7
Provides-Extra: dev
Requires-Dist: pytest; extra == 'dev'
